t265/FrameHandler.py
t265/Tracking.py
t265/__init__.py
t265-0.1.11.dist-info/METADATA
t265-0.1.11.dist-info/WHEEL
t265-0.1.11.dist-info/top_level.txt
t265-0.1.11.dist-info/RECORD
