Metadata-Version: 2.1
Name: t265
Version: 0.1.11
Summary: t265 Tracking camera API wrapper
Author: Yusuke Tanaka
License: LGPLv3
Project-URL: GitHub, https://github.com/Suke0811/Localization_T265
Classifier: Development Status :: 4 - Beta
Classifier: Framework :: Robot Framework
Classifier: Intended Audience :: Developers
Classifier: Intended Audience :: Education
Classifier: Intended Audience :: Science/Research
Classifier: License :: OSI Approved :: GNU Lesser General Public License v3 (LGPLv3)
Classifier: Programming Language :: Python :: 3
Requires-Dist: pyrealsense2 <2.54
Requires-Dist: numpy
